tonapi/__init__.py
tonapi-0.1.0.dist-info/LICENSE
tonapi-0.1.0.dist-info/WHEEL
tonapi-0.1.0.dist-info/METADATA
tonapi-0.1.0.dist-info/RECORD
