Metadata-Version: 2.1
Name: tonapi
Version: 0.1.0
Summary: Python SDK for tonapi.io
Home-page: https://github.com/delpydoc/tonapi
Keywords: ton,the open network,tonapi,sdk
Author: delpydoc
Author-email: delpydoc@proton.me
Requires-Python: >=3.7,<4.0
Classifier: Development Status :: 4 - Beta
Classifier: Intended Audience :: Developers
Classifier: License :: OSI Approved :: MIT License
Classifier: Operating System :: OS Independent
Classifier: Programming Language :: Python :: 3
Classifier: Programming Language :: Python :: 3.7
Classifier: Programming Language :: Python :: 3.8
Classifier: Programming Language :: Python :: 3.9
Classifier: Programming Language :: Python :: 3.10
Classifier: Programming Language :: Python :: 3.11
Classifier: Programming Language :: Python :: 3
Requires-Dist: httpx (>=0.23.1)
Project-URL: Repository, https://github.com/delpydoc/tonapi
